{
  "id": 1,
  "title": "パーレー法：連勝を活かす攻撃的ベッティング戦略",
  "excerpt": "パーレー法は、連勝時に賭け金を倍増させることで利益を最大化する戦略です。リスクを抑えつつ短期間での利益獲得を目指します。",
  "image": "/pa.png",
  "category": "ベッティング戦略",
  "date": "2025-05-23",
  "readTime": "10分",
  "author": "カジノ戦略研究所所属のパー子",
  "content": "<p><strong>概要：</strong>パーレー法は、勝利した際に賭け金を倍にし、連勝によって利益を積み上げる戦略です。負けた場合は初期ベット額に戻すことで、損失を最小限に抑えます。</p><p><strong>使用方法：</strong>例えば、初期ベット額を$10と設定し、勝利するたびに賭け金を倍にします。連勝が続く限り賭け金を増やし、目標連勝数に達したら利益を確定します。</p><p><strong>メリット：</strong>連勝時に利益を最大化でき、損失は初期ベット額に限定されます。リスクを抑えつつ高いリターンを狙える戦略です。</p><p><strong>デメリット：</strong>連勝が続かなければ利益を得られず、連勝中に一度でも負けるとそれまでの利益を失います。適切な勝ち逃げのタイミングが重要です。</p><p><strong>適用可能なゲーム：</strong>バカラ、ブラックジャック、ルーレットなど、勝率が50%前後で配当が2倍のゲームに適しています。</p><p><strong>注意点：</strong>連勝に依存する戦略のため、連勝が難しいゲームでは効果が薄れます。事前に目標連勝数と勝ち逃げのタイミングを設定し、感情に流されずにプレイすることが重要です。</p>"
}
